wgen/__init__.py
wgen/wgen.py
wgen/core/__init__.py
wgen/core/base.py
wgen/core/charset.py
wgen/core/cli.py
wgen/core/help.py
wgen-4.7.9.dist-info/licenses/LICENSE
wgen-4.7.9.dist-info/METADATA
wgen-4.7.9.dist-info/WHEEL
wgen-4.7.9.dist-info/entry_points.txt
wgen-4.7.9.dist-info/top_level.txt
wgen-4.7.9.dist-info/RECORD
